sphire/__init__.py
sphire/bibtex.py
sphire/constants.py
sphire/convert.py
sphire/objects.py
sphire/protocols.conf
sphire/sphire_logo.png
sphire/protocols/__init__.py
sphire/protocols/protocol_cryolo_import.py
sphire/protocols/protocol_cryolo_picking.py
sphire/protocols/protocol_cryolo_training.py
sphire/protocols/protocol_janni_denoise.py
sphire/tests/__init__.py
sphire/tests/test_protocol_cryolo.py
sphire/tests/test_protocol_janni.py
scipion_em_sphire-3.0.8.dist-info/LICENSE
scipion_em_sphire-3.0.8.dist-info/METADATA
scipion_em_sphire-3.0.8.dist-info/WHEEL
scipion_em_sphire-3.0.8.dist-info/entry_points.txt
scipion_em_sphire-3.0.8.dist-info/top_level.txt
scipion_em_sphire-3.0.8.dist-info/RECORD
