Metadata-Version: 2.1
Name: scipion-em-sphire
Version: 3.0.8
Summary: Cryolo picker, training and custom model importer. Janni denoising.
Home-page: https://github.com/scipion-em/scipion-em-sphire
Author: I2PC, Jose Miguel de La Rosa, Jorge Jiménez
Author-email: scipion@cnb.csic.es
License: UNKNOWN
Keywords: scipion cryoem imageprocessing picking denoise scipion-3.0
Platform: UNKNOWN
Requires-Dist: scipion-em
